kondo_ml/__init__.py
kondo_ml/kondo_ml.py
kondo_ml/utils.py
kondo_ml/instance_selection/__init__.py
kondo_ml/instance_selection/_drop.py
kondo_ml/instance_selection/_fish.py
kondo_ml/instance_selection/_fixed_time_window.py
kondo_ml/instance_selection/_full_set.py
kondo_ml/instance_selection/_gradient_shapley.py
kondo_ml/instance_selection/_local_outlier_factor.py
kondo_ml/instance_selection/_mutual_information.py
kondo_ml/instance_selection/_random_selection.py
kondo_ml/instance_selection/_reg_CNN.py
kondo_ml/instance_selection/_reg_ENN.py
kondo_ml/instance_selection/_selcon.py
kondo_ml/instance_selection/base.py
kondo_ml/instance_selection/SELCON/__init__.py
kondo_ml/instance_selection/SELCON/datasets.py
kondo_ml/instance_selection/SELCON/linear.py
kondo_ml/instance_selection/SELCON/model/LinearRegression.py
kondo_ml/instance_selection/SELCON/model/SELCON.py
kondo_ml/instance_selection/SELCON/model/__init__.py
kondo_ml/instance_selection/SELCON/utils/Create_Slices.py
kondo_ml/instance_selection/SELCON/utils/__init__.py
kondo_ml/instance_selection/SELCON/utils/custom_dataset.py
kondo_ml/instance_selection/SELCON/utils/time_series.py
kondo_ml-0.0.10.dist-info/LICENSE
kondo_ml-0.0.10.dist-info/METADATA
kondo_ml-0.0.10.dist-info/WHEEL
kondo_ml-0.0.10.dist-info/top_level.txt
kondo_ml-0.0.10.dist-info/RECORD
