Metadata-Version: 2.1
Name: kondo-ml
Version: 0.0.10
Summary: Python package for instance selection algorithms
Home-page: https://github.com/lurue101/instance-selection-for-regression
Download-URL: https://github.com/lurue101/instance-selection-for-regression/archive/0.0.10.tar.gz
Author: L.Rücker
Author-email: Lukas Rücker <ruecker.lukas@gmail.com>
Project-URL: Homepage, https://github.com/lurue101/instance-selection-for-regression
Classifier: Programming Language :: Python :: 3
Classifier: License :: OSI Approved :: MIT License
Classifier: Operating System :: OS Independent
Requires-Python: >=3.10
License-File: LICENSE
Requires-Dist: numpy
Requires-Dist: pandas
Requires-Dist: scikit-learn
Requires-Dist: torch
Requires-Dist: mutual-info
